{"amount":888.25,"customer_id":246,"day":"2023/05/05","loan_id":"vyv0nykU-JbGU-n7Fv-kQa9-sYLJDtyb0KlY","time":" 22:29:20"}
{"amount":2838.0,"customer_id":840,"day":"2023/05/29","loan_id":"JSzfQMIn-MUVp-Sxxm-ncAU-DNuxxzIHtF7O","time":" 19:23:20"}
{"amount":717.75,"customer_id":309,"day":"2023/05/27","loan_id":"33DQ4Owm-ln6J-o70P-1nVU-iiuyMVQjM3AX","time":" 03:35:38"}
{"amount":1886.5,"customer_id":923,"day":"2023/05/08","loan_id":"Krljs2Z6-MaOS-Rt0x-MEpI-y3jIBzTltfgK","time":" 08:07:32"}
{"amount":206.25,"customer_id":96,"day":"2023/05/09","loan_id":"udLd5m6L-M5KK-3wsL-fhIQ-PxQn8IqAv3Av","time":" 22:38:22"}
{"amount":2563.0,"customer_id":53,"day":"2023/05/24","loan_id":"llr2VIie-lXqg-iUgJ-OC6X-ZwG4wqC0zXsS","time":" 05:16:23"}
{"amount":1457.5,"customer_id":223,"day":"2023/05/09","loan_id":"IraYoKY4-1yUZ-AAim-Dj53-x2rBkN5colYM","time":" 07:28:32"}
